README.md
setup.py
satsure_cloud_utils/__init__.py
satsure_cloud_utils/aws_config_file.py
satsure_cloud_utils/s3_handler_file.py
satsure_cloud_utils.egg-info/PKG-INFO
satsure_cloud_utils.egg-info/SOURCES.txt
satsure_cloud_utils.egg-info/dependency_links.txt
satsure_cloud_utils.egg-info/requires.txt
satsure_cloud_utils.egg-info/top_level.txt