Metadata-Version: 2.1
Name: satsure-cloud-utils
Version: 0.0.26
Summary: A package to navigate SatSure Cloud infrastructure
Home-page: UNKNOWN
Author: Rehan
Author-email: rehan@satsure.co
License: UNKNOWN
Project-URL: Documentation, https://docs-satsure-cloud-utils.netlify.app/
Platform: UNKNOWN
Classifier: Programming Language :: Python :: 3
Classifier: Operating System :: OS Independent
Requires-Python: >=3.8
